lihanpy/__init__.py
lihanpy/lib2.py
lihanpy-0.2.dist-info/METADATA
lihanpy-0.2.dist-info/WHEEL
lihanpy-0.2.dist-info/top_level.txt
lihanpy-0.2.dist-info/RECORD
